PyDSWS_Wrapper/DS_Requests.py
PyDSWS_Wrapper/DS_Response.py
PyDSWS_Wrapper/__init__.py
PyDSWS_Wrapper-0.2.0.dist-info/METADATA
PyDSWS_Wrapper-0.2.0.dist-info/RECORD
PyDSWS_Wrapper-0.2.0.dist-info/WHEEL
PyDSWS_Wrapper-0.2.0.dist-info/top_level.txt
